MANIFEST.in
README.txt
requirements.txt
setup.py
test_requirements.txt
version.txt
debug_utils/__init__.py
debug_utils/debugger.py
nahum_debug_utils.egg-info/PKG-INFO
nahum_debug_utils.egg-info/SOURCES.txt
nahum_debug_utils.egg-info/dependency_links.txt
nahum_debug_utils.egg-info/top_level.txt