Metadata-Version: 1.0
Name: nahum-debug-utils
Version: 1.0.5
Summary: Nahum Debugger
Home-page: http://www.qualisystems.com/
Author: QualiSystems
Author-email: info@qualisystems.com
License: UNKNOWN
Platform: UNKNOWN
